MANIFEST.in
README.md
setup.py
tensorwatch/__init__.py
tensorwatch/array_stream.py
tensorwatch/data_utils.py
tensorwatch/evaler.py
tensorwatch/evaler_utils.py
tensorwatch/file_stream.py
tensorwatch/filtered_stream.py
tensorwatch/image_utils.py
tensorwatch/imagenet_class_index.json
tensorwatch/imagenet_synsets.txt
tensorwatch/imagenet_utils.py
tensorwatch/lv_types.py
tensorwatch/notebook_maker.py
tensorwatch/pytorch_utils.py
tensorwatch/repeated_timer.py
tensorwatch/stream.py
tensorwatch/stream_factory.py
tensorwatch/stream_union.py
tensorwatch/tensor_utils.py
tensorwatch/text_vis.py
tensorwatch/utils.py
tensorwatch/vis_base.py
tensorwatch/visualizer.py
tensorwatch/watcher.py
tensorwatch/watcher_base.py
tensorwatch/watcher_client.py
tensorwatch/zmq_mgmt_stream.py
tensorwatch/zmq_stream.py
tensorwatch/zmq_wrapper.py
tensorwatch.egg-info/PKG-INFO
tensorwatch.egg-info/SOURCES.txt
tensorwatch.egg-info/dependency_links.txt
tensorwatch.egg-info/requires.txt
tensorwatch.egg-info/top_level.txt
tensorwatch/embeddings/__init__.py
tensorwatch/embeddings/tsne_utils.py
tensorwatch/model_graph/__init__.py
tensorwatch/model_graph/torchstat_utils.py
tensorwatch/model_graph/hiddenlayer/__init__.py
tensorwatch/model_graph/hiddenlayer/distiller.py
tensorwatch/model_graph/hiddenlayer/distiller_utils.py
tensorwatch/model_graph/hiddenlayer/ge.py
tensorwatch/model_graph/hiddenlayer/graph.py
tensorwatch/model_graph/hiddenlayer/pytorch_builder.py
tensorwatch/model_graph/hiddenlayer/pytorch_builder_grad.py
tensorwatch/model_graph/hiddenlayer/pytorch_builder_trace.py
tensorwatch/model_graph/hiddenlayer/pytorch_draw_model.py
tensorwatch/model_graph/hiddenlayer/summary_graph.py
tensorwatch/model_graph/hiddenlayer/tf_builder.py
tensorwatch/model_graph/hiddenlayer/transforms.py
tensorwatch/model_graph/torchstat/__init__.py
tensorwatch/model_graph/torchstat/analyzer.py
tensorwatch/model_graph/torchstat/compute_flops.py
tensorwatch/model_graph/torchstat/compute_madd.py
tensorwatch/model_graph/torchstat/compute_memory.py
tensorwatch/model_graph/torchstat/reporter.py
tensorwatch/model_graph/torchstat/stat_tree.py
tensorwatch/mpl/__init__.py
tensorwatch/mpl/bar_plot.py
