Metadata-Version: 2.1
Name: tensorwatch
Version: 0.9.1
Summary: Interactive Realtime Debugging and Visualization for AI
Home-page: https://github.com/microsoft/tensorwatch
Author: Shital Shah
Author-email: shitals@microsoft.com
License: MIT
Platform: UNKNOWN
Classifier: Programming Language :: Python :: 3
Classifier: License :: OSI Approved :: MIT License
Classifier: Operating System :: OS Independent
